MANIFEST.in
README.md
build.py
pyproject.toml
requirements-dev.txt
requirements.txt
setup.py
file_flow/data_io.py
file_flow/events.py
file_flow/handler.py
file_flow/operation.py
file_flow/pipeline.py
file_flow/process.py
file_flow/watcher.py
fileflowio.egg-info/PKG-INFO
fileflowio.egg-info/SOURCES.txt
fileflowio.egg-info/dependency_links.txt
fileflowio.egg-info/requires.txt
fileflowio.egg-info/top_level.txt